convbump/__init__.py
convbump/__main__.py
convbump/conventional.py
convbump/git.py
convbump/py.typed
convbump/version.py
convbump-1.2.0.dist-info/METADATA
convbump-1.2.0.dist-info/WHEEL
convbump-1.2.0.dist-info/entry_points.txt
convbump-1.2.0.dist-info/licenses/LICENSE
convbump-1.2.0.dist-info/RECORD
