Metadata-Version: 2.4
Name: convbump
Version: 1.2.0
Summary: Tool for Conventional Commits
License: BSD-3-Clause
License-File: LICENSE
Keywords: changelog,conventional commit,bump,version,calver
Author: Max Kovykov
Author-email: maxim.kovykov@avast.com
Requires-Python: >=3.8,<4.0
Classifier: Development Status :: 4 - Beta
Classifier: Environment :: Console
Classifier: Intended Audience :: Developers
Classifier: Intended Audience :: System Administrators
Classifier: License :: OSI Approved :: BSD License
Classifier: Operating System :: OS Independent
Classifier: Programming Language :: Python :: 3
Classifier: Programming Language :: Python :: 3.8
Classifier: Programming Language :: Python :: 3.9
Classifier: Programming Language :: Python :: 3.10
Classifier: Programming Language :: Python :: 3.11
Classifier: Programming Language :: Python :: 3.12
Classifier: Programming Language :: Python :: 3.13
Classifier: Programming Language :: Python :: 3.14
Classifier: Topic :: Software Development
Classifier: Topic :: Utilities
Classifier: Typing :: Typed
Requires-Dist: click (>=8.1.7,<9.0.0)
Requires-Dist: dulwich (>=0.21.7,<0.22.0)
Requires-Dist: semver (>=3.0.2,<4.0.0)
